metis_crypto/VERSION
metis_crypto/__init__.py
metis_crypto/common.py
metis_crypto/jwa.py
metis_crypto/jwe.py
metis_crypto/jwk.py
metis_crypto/jws.py
metis_crypto/jwt.py
metis_crypto-0.1.0.dist-info/METADATA
metis_crypto-0.1.0.dist-info/WHEEL
metis_crypto-0.1.0.dist-info/RECORD
