Metadata-Version: 2.1
Name: metis-crypto
Version: 0.1.0
Summary: 
Author: Col Perks
Author-email: wild.fauve@gmail.com
Requires-Python: >=3.11,<4.0
Classifier: Programming Language :: Python :: 3
Classifier: Programming Language :: Python :: 3.11
Requires-Dist: cryptography (>=42.0.5,<43.0.0)
Requires-Dist: typing-extensions (>=4.10.0,<5.0.0)
